SECE/__init__.py
SECE/model.py
SECE/module.py
SECE/utils.py
SECE/utils_clusters.py
SECE/utils_dataset.py
SECE/utils_loss.py
SECE-1.0.3.dist-info/METADATA
SECE-1.0.3.dist-info/WHEEL
SECE-1.0.3.dist-info/top_level.txt
SECE-1.0.3.dist-info/RECORD
