Metadata-Version: 2.1
Name: SECE
Version: 1.0.3
Summary: Spatial region-related embedding and Cell type-related embedding of spatial transcriptomics
Home-page: UNKNOWN
Author: yuanyuanyu
Author-email: UNKNOWN
License: MIT
Platform: UNKNOWN
